pygmentshtmltemplate/__init__.py
pygmentshtmltemplate/docutils.py
pygmentshtmltemplate/py.typed
pygmentshtmltemplate/parsers/__init__.py
pygmentshtmltemplate/templates/__init__.py
pygmentshtmltemplate/templates/default.xml
pygmentshtmltemplate/templates/nodes.py
pygmentshtmltemplate-0.1.0.dist-info/LICENSE.txt
pygmentshtmltemplate-0.1.0.dist-info/METADATA
pygmentshtmltemplate-0.1.0.dist-info/WHEEL
pygmentshtmltemplate-0.1.0.dist-info/entry_points.txt
pygmentshtmltemplate-0.1.0.dist-info/top_level.txt
pygmentshtmltemplate-0.1.0.dist-info/RECORD
