Metadata-Version: 2.1
Name: pygmentshtmltemplate
Version: 0.1.0
Summary: pygments.formatters plugin working together with a template
Home-page: https://github.com/osmatsuda/pygmentshtmltemplate
Author: Osamu Matsuda
Author-email: osmatsuda@gmail.com
Keywords: syntax highlighting
Classifier: Development Status :: 4 - Beta
Classifier: Environment :: Console
Classifier: License :: OSI Approved :: MIT License
Classifier: Operating System :: OS Independent
Classifier: Programming Language :: Python :: 3
Classifier: Intended Audience :: Developers
Classifier: Topic :: Software Development :: Documentation
Requires-Python: >=3.10
License-File: LICENSE.txt
Requires-Dist: pygments (>=2)
Requires-Dist: mako (>=1.1)
